{
  "manifest_etag": "00b1a52ea01cc5cea630fcebff955ebeac553012de065e26a96f98d0a6bb8bdd",
  "manifest_checked_at": "2026-04-13T21:52:10.753643+00:00",
  "last_sync_at": "2026-04-13T21:52:10.757738+00:00",
  "sync_mode": "online_sync",
  "cache_status": "cold",
  "last_error": "Some packages were skipped by delivery-tier policy: openspecy_ftir_core",
  "feed_source": "file:///C:/MaterialScope-web-dash-plotly-migration/pytest_temp/case_392b24e5/mirror",
  "installed_packages": {},
  "cloud_access_enabled": false,
  "cloud_provider_count": 0,
  "last_cloud_lookup_at": "",
  "last_cloud_error": ""
}